text_validator/__init__.py
text_validator/base.py
text_validator/main.py
text_validator/plugins/characters.py
text_validator/plugins/ref_line_format.py
text_validator/plugins/unicode.py
text_validator/plugins/whitespace.py
text_validator-0.3.dist-info/LICENSE
text_validator-0.3.dist-info/METADATA
text_validator-0.3.dist-info/WHEEL
text_validator-0.3.dist-info/entry_points.txt
text_validator-0.3.dist-info/top_level.txt
text_validator-0.3.dist-info/RECORD
