Metadata-Version: 2.1
Name: text-validator
Version: 0.3
Summary: pluggable command-line tool for validating the formatting and orthography of text files
Home-page: http://github.com/jtauber/text-validator
Author: James Tauber
Author-email: jtauber@jtauber.com
License: MIT
Platform: UNKNOWN
Classifier: Development Status :: 4 - Beta
Classifier: License :: OSI Approved :: MIT License
Classifier: Programming Language :: Python :: 3.6
Classifier: Programming Language :: Python :: 3.7
Classifier: Programming Language :: Python :: 3.8
Classifier: Topic :: Text Processing
